jmble/__init__.py
jmble/_types/__init__.py
jmble/_types/_attr_dict.py
jmble/cli_tools/__init__.py
jmble/cli_tools/byte_calc.py
jmble/cli_tools/config_cli.py
jmble/cli_tools/gpush.py
jmble/cli_tools/prolog.py
jmble/cli_tools/version_manager.py
jmble/config/__init__.py
jmble/config/configurator.py
jmble/config/option_args.py
jmble/general_modules/__init__.py
jmble/general_modules/file_utils.py
jmble/general_modules/utils.py
jmble/jmble_logging.py
jmble-0.0.39.dist-info/METADATA
jmble-0.0.39.dist-info/WHEEL
jmble-0.0.39.dist-info/entry_points.txt
jmble-0.0.39.dist-info/RECORD
